main.py
gitai_tool-0.4.0.dist-info/METADATA
gitai_tool-0.4.0.dist-info/WHEEL
gitai_tool-0.4.0.dist-info/entry_points.txt
gitai_tool-0.4.0.dist-info/top_level.txt
gitai_tool-0.4.0.dist-info/RECORD
