Metadata-Version: 2.4
Name: gitai-tool
Version: 0.4.0
Summary: Generate summaries and code reviews for GitLab Merge Requests or GitHub Pull Requests using LLM
Author: Aleksandar Farkov
License: MIT
Keywords: git,gitlab,github,merge-requests,pull-requests,cli,llm,ai,summaries,code-review
Classifier: Programming Language :: Python :: 3
Classifier: License :: OSI Approved :: MIT License
Classifier: Operating System :: OS Independent
Classifier: Environment :: Console
Classifier: Topic :: Software Development :: Version Control :: Git
Requires-Python: >=3.8
Requires-Dist: python-gitlab>=3.0.0
Requires-Dist: google-generativeai>=0.3.0
Requires-Dist: toml>=0.10.2
